{
  "blog": "triplog",
  "site_url": "https://app.baremi542.com",
  "keyword": "제주도 1박2일 혼자 여행 코스",
  "title": "제주도 1박2일 혼자 여행 2026 완벽 가이드 – 코스·숙소·비용 총정리",
  "category": "여행",
  "status": "pending_publish",
  "created_at": "2026-05-29T07:00:00",
  "content": "<h2>제주도 혼자 여행, 1박 2일로 충분할까요?</h2>\n<p>제주도 혼자 여행은 자유롭고 자신만의 속도로 움직일 수 있어 최근 솔로 트래블러 사이에서 큰 인기를 끌고 있습니다. 1박 2일이라는 짧은 일정이지만, 렌터카를 활용하면 제주의 핵심 명소를 알차게 돌아볼 수 있습니다. 2026년 기준으로 혼자 여행에 최적화된 코스, 숙소, 비용을 정리했습니다.</p>\n\n<img src=\"https://loremflickr.com/800/450/jeju,korea/1\" alt=\"제주도 혼자 여행\">\n\n<h2>1박 2일 추천 코스</h2>\n<p>제주공항 도착부터 출발까지 효율적으로 움직이는 코스입니다. 렌터카 기준으로 작성했습니다.</p>\n\n<h3>1일차 – 서부·중부 코스</h3>\n<ul>\n<li><strong>오전:</strong> 제주국제공항 도착 → 렌터카 픽업 (공항 근처 렌터카 업체 집중)</li>\n<li><strong>오전 11시:</strong> 제주 오일장 (5·10일 장날이면 필수) 또는 이호테우해변</li>\n<li><strong>오후 1시:</strong> 점심 – 흑돼지 구이 (제주시 연동 맛집 거리)</li>\n<li><strong>오후 2시:</strong> 협재해수욕장 + 한림공원 (비양도 전망)</li>\n<li><strong>오후 4시:</strong> 오설록 티뮤지엄 + 이니스프리 제주하우스 (인증샷 명소)</li>\n<li><strong>오후 6시:</strong> 산방산 일몰 감상</li>\n<li><strong>저녁:</strong> 서귀포 숙소 체크인 → 천지연폭포 야경 (숙소 근처면 도보)</li>\n</ul>\n\n<h3>2일차 – 동부 코스</h3>\n<ul>\n<li><strong>오전 7시:</strong> 성산일출봉 일출 감상 (혼자 여행의 하이라이트)</li>\n<li><strong>오전 9시:</strong> 섭지코지 산책 + 아쿠아플라넷 선택</li>\n<li><strong>오전 11시:</strong> 만장굴 (세계자연유산, 시원한 동굴 탐방)</li>\n<li><strong>오후 1시:</strong> 점심 – 고기국수 또는 갈치조림 (제주 향토 음식)</li>\n<li><strong>오후 2시:</strong> 김녕해수욕장 or 월정리해변 (에메랄드빛 바다)</li>\n<li><strong>오후 4시:</strong> 공항으로 이동 + 렌터카 반납</li>\n<li><strong>저녁:</strong> 제주공항 출발</li>\n</ul>\n\n<img src=\"https://loremflickr.com/800/450/jeju,travel/2\" alt=\"제주도 여행 코스\">\n\n<h2>혼자 여행 숙소 추천 유형</h2>\n<p>1인 여행자에게 맞는 숙소 유형을 예산별로 정리했습니다.</p>\n\n<h3>게스트하우스 (저예산, 1~4만 원/박)</h3>\n<ul>\n<li>제주시·서귀포 시내에 1인실 게스트하우스 다수</li>\n<li>다른 여행자와 교류 가능 (파티룸, 공용 주방 등)</li>\n<li>추천 지역: 제주시 구도심, 서귀포 이중섭 거리 근처</li>\n</ul>\n\n<h3>에어비앤비·호스텔 (중저가, 5~10만 원/박)</h3>\n<ul>\n<li>독채 또는 1인실 프라이빗 숙소</li>\n<li>조식 포함 여부 확인 필수</li>\n</ul>\n\n<h3>감성 펜션·소형 호텔 (중가, 10~20만 원/박)</h3>\n<ul>\n<li>제주 로컬 감성 숙소에서 프라이빗 시간 즐기기</li>\n<li>성산·월정리·협재 근처 풍경 좋은 숙소 많음</li>\n</ul>\n\n<h2>혼자 제주 여행 예상 비용</h2>\n<p>1박 2일 혼자 여행 기준 예상 경비입니다. (서울 출발 기준)</p>\n<ul>\n<li><strong>항공권:</strong> 5~12만 원 (왕복, 이른 예약 시 저가)</li>\n<li><strong>렌터카:</strong> 4~8만 원/일 (경차·소형 기준)</li>\n<li><strong>숙소:</strong> 3~10만 원/박 (게스트하우스~소형 호텔)</li>\n<li><strong>식비:</strong> 3~6만 원/일 (1인 기준, 향토 음식 위주)</li>\n<li><strong>입장료·기타:</strong> 2~5만 원 (성산일출봉, 만장굴 등)</li>\n<li><strong>총 예상:</strong> <strong>20~40만 원</strong> (절약형~중간 기준)</li>\n</ul>\n\n<img src=\"https://loremflickr.com/800/450/sunrise,jeju/3\" alt=\"성산일출봉 일출\">\n\n<h2>혼자 여행 꿀팁</h2>\n<ul>\n<li><strong>렌터카 필수:</strong> 제주 대중교통은 배차 간격이 길어 렌터카 없이는 이동 불편</li>\n<li><strong>항공권 조기 예매:</strong> 2~3개월 전 예약 시 절반 가격에 구매 가능</li>\n<li><strong>성수기 피하기:</strong> 7~8월보다 5~6월, 9~10월이 물가·인파 모두 여유</li>\n<li><strong>날씨 앱 필수:</strong> 제주는 날씨 변화가 크므로 수시 확인</li>\n<li><strong>해녀 체험:</strong> 혼자서도 참여 가능한 소규모 체험 프로그램 활용</li>\n<li><strong>카카오맵·네이버맵:</strong> 제주 맛집·관광지 리뷰 미리 즐겨찾기 저장</li>\n</ul>\n\n<h2>제주도 혼자 여행 FAQ</h2>\n<p><strong>Q. 혼자 제주 여행, 안전한가요?</strong><br>\nA. 제주도는 치안이 매우 안전한 여행지입니다. 야간 해안도로 운전만 조심하면 됩니다.</p>\n<p><strong>Q. 렌터카 없이 1박2일 가능한가요?</strong><br>\nA. 제주시 구도심 위주로만 이동하면 버스로도 가능하지만, 성산·서귀포·협재 등 원하는 명소를 자유롭게 다니려면 렌터카를 강력 추천합니다.</p>\n<p><strong>Q. 1박 2일에 독도(울릉도)도 같이 갈 수 있나요?</strong><br>\nA. 제주도와 울릉도는 별개의 여정이므로 동시에 가기는 어렵습니다. 각각 별도 일정을 잡으세요.</p>\n\n<p>제주도 1박 2일 혼자 여행은 렌터카와 사전 계획만 잘 세우면 누구나 알찬 시간을 보낼 수 있습니다. 성산일출봉의 일출, 협재의 에메랄드 바다, 제주 흑돼지의 맛까지 — 짧지만 강렬한 제주의 매력을 마음껏 즐기세요.</p>"
}